{
  "categories": [
    "Electoral",
    "Political Speech",
    "Monetary Policy",
    "Polling & Approval",
    "Government Operations",
    "Military & Security",
    "Appointments",
    "International",
    "Legislative",
    "Other",
    "Judicial",
    "Leadership Changes",
    "Crisis & Emergency",
    "Regulatory"
  ],
  "total_markets": [
    28933,
    10416,
    9674,
    4032,
    4022,
    3370,
    3062,
    2837,
    1649,
    1217,
    1075,
    939,
    585,
    362
  ],
  "avg_volume_k": [
    461.5,
    34.1,
    345.4,
    10.4,
    144.7,
    637.8,
    317.7,
    304.7,
    25.0,
    196.6,
    143.2,
    340.8,
    107.8,
    559.0
  ],
  "median_volume_k": [
    13.6,
    8.1,
    6.1,
    17.1,
    24.2,
    95.5,
    31.5,
    39.0,
    15.9,
    24.1,
    29.3,
    49.9,
    39.4,
    37.1
  ],
  "total_volume_m": [
    13351.2,
    355.0,
    3341.2,
    41.8,
    582.0,
    2149.3,
    972.9,
    864.5,
    41.2,
    239.2,
    153.9,
    320.0,
    63.1,
    202.4
  ]
}