{
  "cohorts": {
    "5d": {
      "n": 1646,
      "days": [
        5,
        4,
        3,
        2,
        1
      ],
      "scores": [
        0.0762,
        0.0738,
        0.071,
        0.0693,
        0.0674
      ]
    },
    "15d": {
      "n": 1409,
      "days": [
        15,
        10,
        5,
        4,
        3,
        2,
        1
      ],
      "scores": [
        0.0674,
        0.0603,
        0.0576,
        0.0567,
        0.0561,
        0.0562,
        0.0554
      ]
    },
    "30d": {
      "n": 1247,
      "days": [
        30,
        25,
        20,
        15,
        10,
        5,
        4,
        3,
        2,
        1
      ],
      "scores": [
        0.0974,
        0.076,
        0.064,
        0.0574,
        0.054,
        0.0509,
        0.0504,
        0.0495,
        0.0491,
        0.0486
      ]
    },
    "60d": {
      "n": 832,
      "days": [
        60,
        55,
        50,
        45,
        40,
        35,
        30,
        25,
        20,
        15,
        10,
        5,
        4,
        3,
        2,
        1
      ],
      "scores": [
        0.0954,
        0.0897,
        0.0876,
        0.0786,
        0.0771,
        0.0716,
        0.0788,
        0.0639,
        0.0534,
        0.0495,
        0.0448,
        0.0441,
        0.0449,
        0.0446,
        0.0445,
        0.0438
      ]
    }
  }
}