{
  "categories": [
    "Military & Security",
    "Judicial",
    "Electoral",
    "Government Operations",
    "Crisis & Emergency",
    "Monetary Policy",
    "International",
    "Political Speech",
    "Leadership Changes",
    "Other",
    "Polling & Approval",
    "Regulatory",
    "Appointments",
    "Legislative"
  ],
  "n_markets": [
    524,
    251,
    2842,
    214,
    29,
    613,
    589,
    629,
    226,
    243,
    76,
    116,
    348,
    192
  ],
  "spread_median": [
    22.91,
    25.28,
    30.39,
    33.73,
    34.54,
    34.65,
    34.74,
    40.38,
    44.37,
    46.86,
    48.67,
    48.84,
    52.25,
    57.47
  ],
  "depth_median": [
    85278.0,
    26594.0,
    67936.0,
    48484.0,
    60677.0,
    38407.0,
    56299.0,
    6656.0,
    36109.0,
    21473.0,
    25833.0,
    31442.0,
    59179.0,
    21168.0
  ],
  "polymarket": {
    "spread": [
      23.02,
      29.61,
      51.7,
      33.04,
      28.54,
      39.46,
      34.33,
      46.05,
      47.84,
      47.75,
      60.86,
      47.03,
      59.49,
      44.01
    ],
    "depth": [
      89539.0,
      76301.0,
      83897.0,
      72551.0,
      79848.0,
      43326.0,
      82102.0,
      5910.0,
      63208.0,
      21547.0,
      28503.0,
      49232.0,
      63714.0,
      49820.0
    ],
    "count": [
      511,
      106,
      1731,
      143,
      20,
      412,
      404,
      528,
      133,
      105,
      40,
      62,
      225,
      44
    ]
  },
  "kalshi": {
    "spread": [
      16.76,
      22.51,
      13.19,
      38.86,
      116.06,
      24.92,
      37.52,
      15.17,
      36.2,
      44.99,
      27.89,
      57.4,
      30.42,
      62.81
    ],
    "depth": [
      16053.0,
      11934.0,
      18887.0,
      15623.0,
      6999.0,
      19792.0,
      13197.0,
      37538.0,
      19130.0,
      21453.0,
      16968.0,
      17468.0,
      19648.0,
      12279.0
    ],
    "count": [
      13,
      145,
      1111,
      71,
      9,
      201,
      185,
      101,
      93,
      138,
      36,
      54,
      123,
      148
    ]
  },
  "total_markets": 6892,
  "total_volume": 5017690982.439432
}